evil_blocker/__init__.py
evil_blocker-0.1.0.dist-info/WHEEL
evil_blocker-0.1.0.dist-info/entry_points.txt
evil_blocker-0.1.0.dist-info/METADATA
evil_blocker-0.1.0.dist-info/RECORD
