Metadata-Version: 2.3
Name: evil-blocker
Version: 0.1.0
Summary: protect your personal server from abusive activity
Author: ZhuangYumin
Author-email: ZhuangYumin <zymx@pm.me>
Requires-Python: >=3.12.11
